src/__init__.py
src/eva_clip_model.py
autodistill_eva_clip-0.1.0.dist-info/LICENSE
autodistill_eva_clip-0.1.0.dist-info/METADATA
autodistill_eva_clip-0.1.0.dist-info/WHEEL
autodistill_eva_clip-0.1.0.dist-info/top_level.txt
autodistill_eva_clip-0.1.0.dist-info/RECORD
