Metadata-Version: 2.1
Name: autodistill-eva-clip
Version: 0.1.0
Summary: EvaClip module for use with Autodistill
Home-page: https://github.com/lab176344/autodistill-evaclip/
Author: Lakshman
Author-email: lakshman@moiiai.com
License: UNKNOWN
Platform: UNKNOWN
Classifier: Programming Language :: Python :: 3
Classifier: License :: OSI Approved :: MIT License
Classifier: Operating System :: OS Independent
Requires-Python: >=3.7
License-File: LICENSE
Requires-Dist: torch
Requires-Dist: supervision
Requires-Dist: numpy
Requires-Dist: ultralytics
Requires-Dist: autodistill
Requires-Dist: roboflow
Requires-Dist: transformers
Provides-Extra: dev
Requires-Dist: flake8 ; extra == 'dev'
Requires-Dist: black ==22.3.0 ; extra == 'dev'
Requires-Dist: isort ; extra == 'dev'
Requires-Dist: twine ; extra == 'dev'
Requires-Dist: pytest ; extra == 'dev'
Requires-Dist: wheel ; extra == 'dev'
